<?xml version="1.0" encoding="utf-8" ?>
<Records>
  <Record>
    <Title updatetimes="2013-5-24">立信培训系统更新日志|更新时间：2013-5-24</Title>
    <Content mode="我的培训计划">增加“是否可折算CPA学时”；</Content>
    <Content mode="我的培训计划">我的培训计划-在年度计划中新增课程，增加“培训形式”、“学时”字段，在月度计划以及相关的页面也要相应的显示；</Content>
    <Content mode="我的培训计划">我的培训计划-在月度计划的“新增课程”弹出框中，“预计开课时间”字段要精确到时、分，另外加上“地点”字段；</Content>
    <Content mode="我的培训计划">我的培训计划—月度培训选项卡页面列表增加“学时”、“地点”字段；</Content>
    <Content mode="我的培训计划">我的培训计划：年度和月度页面都要加（合计：总学时）；</Content>
    <Content mode="培训管理">在“集中授课课程开设”页面：增加“框架内/外”字段、开设集中授课页面；</Content>
    <Content mode="培训管理">课程管理——课程列表：增设筛选项“计划内”“计划外”“能力框架内”“能力框架外”；</Content>
    <Content mode="我的课程">集中授课课程、视频课程中的课后评估，所有都改成必填项；</Content>
    <Content mode="培训管理">在线测试结束后，有跳出框提示“通过/未通过”，如果通过提示“恭喜，您已通过本次测试，可查看获取学时情况”，未通过则要提示“抱歉，您未能通过本次测试，本课程还剩余X次考试机会”；</Content>
    <Content mode="我的课程">为了方便后台统计学员学习进度，视频课件若来源于第三方服务器，需对方提供哪些信息；</Content>
    <Content mode="我的培训首页">修复了我的培训首页，未被开放权限预订或未被指定的人员也看到了公告和最新开课栏内这门课程的信息；</Content>
    <Content mode="课程预定查询">课程预订级别分布，按已经预订人员来进行统计；</Content>
    <Content mode="课程列表">课程学时获得的比重，在整体参数配置的基础上，针对个别课程也可以单独配置；</Content>
    <Content mode="课程预定查询">课程预订查询—（集中授课课程预订详情、CPA课程预订详情）页面，列表中增加报名时间字段，按报名时间的降序排列；</Content>
    <Content mode="课程列表">集中授课—在线测试，允许考试时间改为以小时为单位，同时相关的参数配置（在线测试允许答题时间）也要改成以小时为单位（由于理解偏差）；</Content>
    <Content mode="参数配置">请假模板将“（如临时被安排到XX公司审计项目中）”这句话去掉；</Content>
    <Content mode="我的考勤">我的考勤页面，当课程还未开始时，考勤状态显示“课程未开始”；</Content>
    <Content mode="我的培训首页">我的培训首页，我的考勤列表只显示课程已经结束的，考勤信息；</Content>
  </Record>
</Records>